prototorch_qu/__init__.py
prototorch_qu-0.0.0.dist-info/LICENSE
prototorch_qu-0.0.0.dist-info/METADATA
prototorch_qu-0.0.0.dist-info/WHEEL
prototorch_qu-0.0.0.dist-info/entry_points.txt
prototorch_qu-0.0.0.dist-info/top_level.txt
prototorch_qu-0.0.0.dist-info/RECORD
